{"index":"lion","name":"Lion","size":"Large","type":"beast","cr":1.0,"xp":200,"hp":26,"hp_roll":"26d4d10","ac":12,"speed":"50 ft.","abilities":{"str":17,"dex":15,"con":13,"int":3,"wis":12,"cha":8},"actions":[{"name":"Bite","desc":"Melee Weapon Attack: +5 to hit, reach 5 ft., one target. Hit: 7 (1d8 + 3) piercing damage.","attack_bonus":5,"damage":[{"dice":"1d8+3","type":"piercing"}],"dc":null},{"name":"Claw","desc":"Melee Weapon Attack: +5 to hit, reach 5 ft., one target. Hit: 6 (1d6 + 3) slashing damage.","attack_bonus":5,"damage":[{"dice":"1d6+3","type":"slashing"}],"dc":null}],"reactions":[],"legendary_actions":[],"traits":[{"name":"Keen Smell","desc":"The lion has advantage on Wisdom (Perception) checks that rely on smell."},{"name":"Pack Tactics","desc":"The lion has advantage on an attack roll against a creature if at least one of the lion's allies is within 5 ft. of the creature and the ally isn't incapacitated."},{"name":"Pounce","desc":"If the lion moves at least 20 ft. straight toward a creature and then hits it with a claw attack on the same turn, that target must succeed on a DC 13 Strength saving throw or be knocked prone. If the target is prone, the lion can make one bite attack against it as a bonus action."},{"name":"Running Leap","desc":"With a 10-foot running start, the lion can long jump up to 25 ft.."}],"senses":{"passive_perception":13},"languages":"","proficiencies":[{"proficiency":{"index":"skill-perception","name":"Skill: Perception","url":"/api/proficiencies/skill-perception"},"value":3},{"proficiency":{"index":"skill-stealth","name":"Skill: Stealth","url":"/api/proficiencies/skill-stealth"},"value":6}]}