{
  "index": "ring-of-regeneration",
  "name": "Ring of Regeneration",
  "category": "magic-items",
  "item_type": "ring",
  "rarity": "rare",
  "requires_attunement": true,
  "attuned": false,
  "ac_bonus": 0,
  "saving_throw_bonus": 0,
  "ability_bonuses": {},
  "actions": [],
  "effects": [],
  "cost": "100 gp",
  "price": 10000,
  "sell_price": 5000,
  "weight": 1,
  "desc": [
    "Ring, very rare (requires attunement)",
    "While wearing this ring, you regain 1d6 hit points every 10 minutes, provided that you have at least 1 hit point. If you lose a body part, the ring causes the missing part to regrow and return to full functionality after 1d6 + 1 days if you have at least 1 hit point the whole time."
  ]
}